{
  "header": "Constructors standings",
  "generatedAtUtc": "2026-03-08T08:47:13.322Z",
  "source": "https://www.formula1.com/en/results/2026/team",
  "meta": {
    "mode": "PLACEHOLDER",
    "season": 2026,
    "parseReason": "heading_not_found"
  },
  "constructors": [
    {
      "team": "Alpine",
      "position": "-",
      "points": "-",
      "wins": "-",
      "teamLogoPng": "https://mredman48.github.io/F1-standings/teamlogos/2025_alpine_color_v2.png?v=1772959633321",
      "placeholder": true
    },
    {
      "team": "Aston Martin",
      "position": "-",
      "points": "-",
      "wins": "-",
      "teamLogoPng": "https://mredman48.github.io/F1-standings/teamlogos/2025_aston-martin_color_v2.png?v=1772959633321",
      "placeholder": true
    },
    {
      "team": "Audi",
      "position": "-",
      "points": "-",
      "wins": "-",
      "teamLogoPng": "https://mredman48.github.io/F1-standings/teamlogos/audi_logo_colored.png?v=1772959633321",
      "placeholder": true
    },
    {
      "team": "Cadillac",
      "position": "-",
      "points": "-",
      "wins": "-",
      "teamLogoPng": "https://mredman48.github.io/F1-standings/teamlogos/2025_cadillac_color_v2.png?v=1772959633321",
      "placeholder": true
    },
    {
      "team": "Ferrari",
      "position": "-",
      "points": "-",
      "wins": "-",
      "teamLogoPng": "https://mredman48.github.io/F1-standings/teamlogos/2025_ferrari_color_v2.png?v=1772959633321",
      "placeholder": true
    },
    {
      "team": "Haas",
      "position": "-",
      "points": "-",
      "wins": "-",
      "teamLogoPng": "https://mredman48.github.io/F1-standings/teamlogos/2025_haas_color_v2.png?v=1772959633321",
      "placeholder": true
    },
    {
      "team": "McLaren",
      "position": "-",
      "points": "-",
      "wins": "-",
      "teamLogoPng": "https://mredman48.github.io/F1-standings/teamlogos/2025_mclaren_color_v2.png?v=1772959633321",
      "placeholder": true
    },
    {
      "team": "Mercedes",
      "position": "-",
      "points": "-",
      "wins": "-",
      "teamLogoPng": "https://mredman48.github.io/F1-standings/teamlogos/2025_mercedes_color_v2.png?v=1772959633321",
      "placeholder": true
    },
    {
      "team": "Red Bull",
      "position": "-",
      "points": "-",
      "wins": "-",
      "teamLogoPng": "https://mredman48.github.io/F1-standings/teamlogos/2025_red-bull_color_v2.png?v=1772959633321",
      "placeholder": true
    },
    {
      "team": "VCARB",
      "position": "-",
      "points": "-",
      "wins": "-",
      "teamLogoPng": "https://mredman48.github.io/F1-standings/teamlogos/2025_vcarb_color_v2.png?v=1772959633322",
      "placeholder": true
    },
    {
      "team": "Williams",
      "position": "-",
      "points": "-",
      "wins": "-",
      "teamLogoPng": "https://mredman48.github.io/F1-standings/teamlogos/2025_williams_color_v2.png?v=1772959633322",
      "placeholder": true
    }
  ]
}