{
  "header": "Haas standings",
  "generatedAtUtc": "2026-03-08T16:31:58.413Z",
  "sources": {
    "driverStandings": "f1_driver_standings.json",
    "constructorStandings": "f1_constructors_standings.json",
    "bestResults": "OpenF1 sessions?year=YYYY&session_name=Race + session_result?driver_number=NN"
  },
  "haas": {
    "team": "Haas",
    "teamLogoPng": "https://mredman48.github.io/F1-standings/teamlogos/2025_haas_color_v2.png",
    "teamStanding": {
      "team": "Haas",
      "position": "P5",
      "points": 6,
      "wins": 0
    }
  },
  "lastRace": {
    "season": "2026",
    "round": "latest",
    "raceName": "Flag of Australia Australia",
    "date": "08 Mar",
    "timeUtc": "1:23:06.801",
    "circuit": {
      "name": "Albert Park Grand Prix Circuit",
      "locality": "Melbourne",
      "country": "Australia"
    },
    "winner": {
      "name": "George Russell RUS",
      "team": "Mercedes",
      "laps": 58
    }
  },
  "drivers": [
    {
      "firstName": "Oliver",
      "lastName": "Bearman",
      "code": "BEA",
      "driverNumber": 87,
      "numberImageUrl": "https://mredman48.github.io/F1-standings/driver-numbers/driver-number-87.png",
      "headshotUrl": "https://mredman48.github.io/F1-standings/headshots/oliver-bearman.png",
      "position": "P7",
      "points": 6,
      "wins": 0,
      "team": "Haas",
      "bestResult": {
        "position": "P7",
        "raceName": "-",
        "round": "1279",
        "date": "2026-03-08T04:00:00+00:00",
        "circuit": "Melbourne",
        "location": {
          "locality": "Melbourne",
          "country": "Australia"
        },
        "sessionKey": 11234,
        "meetingKey": 1279
      }
    },
    {
      "firstName": "Esteban",
      "lastName": "Ocon",
      "code": "OCO",
      "driverNumber": 31,
      "numberImageUrl": "https://mredman48.github.io/F1-standings/driver-numbers/driver-number-31.png",
      "headshotUrl": "https://mredman48.github.io/F1-standings/headshots/esteban-ocon.png",
      "position": "P11",
      "points": 0,
      "wins": 0,
      "team": "Haas",
      "bestResult": {
        "position": "P11",
        "raceName": "-",
        "round": "1279",
        "date": "2026-03-08T04:00:00+00:00",
        "circuit": "Melbourne",
        "location": {
          "locality": "Melbourne",
          "country": "Australia"
        },
        "sessionKey": 11234,
        "meetingKey": 1279
      }
    }
  ]
}